Parameter.v
// =========================================================================
// Practical 4: StarCore-1 — Single-Cycle Processor in Verilog
// =========================================================================
//
// GROUP NUMBER: 11
//
// MEMBERS:
//   - Joshua Smith,    SMTJOS022
//   - Ebrahim Bhyat,   BHYEBR002
//   - Tlangalani Tembe, TMBTLA001

`timescale 1ns / 1ps

`define WORDWIDTH 16
`define INSTRUCTION_DEPTH 16
`define DATA_DEPTH 8
`define SIM_TIME 1

ALU_Control.v
// =========================================================================
// Practical 4: StarCore-1 — Single-Cycle Processor in Verilog
// =========================================================================
//
// GROUP NUMBER: 11
//
// MEMBERS:
//   - Joshua Smith,    SMTJOS022
//   - Ebrahim Bhyat,   BHYEBR002
//   - Tlangalani Tembe, TMBTLA001

`include "Parameter.v"

module ALU_Control (
    input [1:0] ALUOp,
    input [3:0] opcode,

    output reg [2:0] ALUcnt

);
    always @(*) begin
        // Good practice: assign a safe default
        ALUcnt = 3'b000; 

        case (ALUOp)
            2'b00: begin
                // R-type Look at the opcode to decide.
                case (opcode)
                    4'b0010: ALUcnt = 3'b000; // ADD
                    4'b0011: ALUcnt = 3'b001; // SUB
                    4'b0100: ALUcnt = 3'b100; // NOT
                    4'b0101: ALUcnt = 3'b101; // SHL
                    4'b0110: ALUcnt = 3'b110; // SHR
                    4'b0111: ALUcnt = 3'b010; // AND
                    4'b1000: ALUcnt = 3'b011; // OR 
                    4'b1001: ALUcnt = 3'b111; // SLT
                    
                    default: ALUcnt = 3'b000;
                endcase
            end
            
            2'b01: begin
                // Branch: Force a subtraction.
                ALUcnt = 3'b001;
            end
            
            2'b10: begin
                // Load/Store: Force an addition.
                ALUcnt = 3'b000;
                
            end

            default: ALUcnt = 3'b000;
        endcase
    end


endmodule

ALU_Control_tb.v
`timescale 1ns / 1ps
`include "Parameter.v"
`include "ALU_Control.v" 

// iverilog -Wall -o aluctrl_sim ALU_Control_tb.v && ./aluctrl_sim && gtkwave alu_control_waves.vcd &

module ALU_Control_tb;

    reg [1:0] ALUOp;
    reg [3:0] opcode;

    wire [2:0] ALUcnt;

    // UUT
    ALU_Control uut (
        .ALUOp(ALUOp),
        .opcode(opcode),
        .ALUcnt(ALUcnt)
    );

    initial begin
        // Setup waveform dumping for GTKWave
        $dumpfile("alu_control_waves.vcd");
        $dumpvars(0, ALU_Control_tb);

        $display("--- Starting ALU Control Unit Tests ---");

        // Test 1: Load/Store (ALUOp = 10)
        // Should force an ADD (000), ignoring the opcode
        ALUOp = 2'b10; 
        opcode = 4'b0000; // Supplying LD opcode, but it shouldn't matter
        #10;
        
        if (ALUcnt !== 3'b000) $display("FAIL T1: Load/Store did not output 000. Got: %b", ALUcnt);
        else $display("PASS T1: Load/Store (ALUOp=10) forced ADD (000)");

        // Test 2: Branch (ALUOp = 01)
        // Should force a SUB (001), ignoring the opcode
        ALUOp = 2'b01; 
        opcode = 4'b1011; // Supplying BEQ opcode, but it shouldn't matter
        #10;
        
        if (ALUcnt !== 3'b001) $display("FAIL T2: Branch did not output 001. Got: %b", ALUcnt);
        else $display("PASS T2: Branch (ALUOp=01) forced SUB (001)");

        // Test 3: R-Type Instructions (ALUOp = 00)
        // Should translate based entirely on the opcode
        ALUOp = 2'b00;

        // Test ADD
        opcode = 4'b0010; #10;
        if (ALUcnt !== 3'b000) $display("FAIL T3.1: R-Type ADD output wrong. Got: %b", ALUcnt);
        else $display("PASS T3.1: R-Type ADD (0010) correctly mapped to 000");

        // Test SUB
        opcode = 4'b0011; #10;
        if (ALUcnt !== 3'b001) $display("FAIL T3.2: R-Type SUB output wrong. Got: %b", ALUcnt);
        else $display("PASS T3.2: R-Type SUB (0011) correctly mapped to 001");

        // Test INV
        opcode = 4'b0100; #10;
        if (ALUcnt !== 3'b100) $display("FAIL T3.3: R-Type INV output wrong. Got: %b", ALUcnt);
        else $display("PASS T3.3: R-Type INV (0100) correctly mapped to 100");

        // Test SHL
        opcode = 4'b0101; #10;
        if (ALUcnt !== 3'b101) $display("FAIL T3.4: R-Type SHL output wrong. Got: %b", ALUcnt);
        else $display("PASS T3.4: R-Type SHL (0101) correctly mapped to 101");

        // Test SHR
        opcode = 4'b0110; #10;
        if (ALUcnt !== 3'b110) $display("FAIL T3.5: R-Type SHR output wrong. Got: %b", ALUcnt);
        else $display("PASS T3.5: R-Type SHR (0110) correctly mapped to 110");

        // Test AND
        opcode = 4'b0111; #10;
        if (ALUcnt !== 3'b010) $display("FAIL T3.6: R-Type AND output wrong. Got: %b", ALUcnt);
        else $display("PASS T3.6: R-Type AND (0111) correctly mapped to 010");

        // Test OR
        opcode = 4'b1000; #10;
        if (ALUcnt !== 3'b011) $display("FAIL T3.7: R-Type OR output wrong. Got: %b", ALUcnt);
        else $display("PASS T3.7: R-Type OR  (1000) correctly mapped to 011");

        // Test SLT
        opcode = 4'b1001; #10;
        if (ALUcnt !== 3'b111) $display("FAIL T3.8: R-Type SLT output wrong. Got: %b", ALUcnt);
        else $display("PASS T3.8: R-Type SLT (1001) correctly mapped to 111");

        #20;
        $display("--- ALU Control Tests Complete ---");
        $finish;
    end

endmodule

alu_control_waves.vcd
$date
	Wed Apr 22 07:29:05 2026
$end
$version
	Icarus Verilog
$end
$timescale
	1ps
$end
$scope module ALU_Control_tb $end
$var wire 3 ! ALUcnt [2:0] $end
$var reg 2 " ALUOp [1:0] $end
$var reg 4 # opcode [3:0] $end
$scope module uut $end
$var wire 2 $ ALUOp [1:0] $end
$var wire 4 % opcode [3:0] $end
$var reg 3 & ALUcnt [2:0] $end
$upscope $end
$upscope $end
$enddefinitions $end
$comment Show the parameter values. $end
$dumpall
$end
#0
$dumpvars
b0 &
b0 %
b10 $
b0 #
b10 "
b0 !
$end
#10000
b1 !
b1 &
b1011 #
b1011 %
b1 "
b1 $
#20000
b0 !
b0 &
b10 #
b10 %
b0 "
b0 $
#30000
b1 !
b1 &
b11 #
b11 %
#40000
b100 !
b100 &
b100 #
b100 %
#50000
b101 !
b101 &
b101 #
b101 %
#60000
b110 !
b110 &
b110 #
b110 %
#70000
b10 !
b10 &
b111 #
b111 %
#80000
b11 !
b11 &
b1000 #
b1000 %
#90000
b111 !
b111 &
b1001 #
b1001 %
