Parameter.v
// =========================================================================
// Practical 4: StarCore-1 — Single-Cycle Processor in Verilog
// =========================================================================
//
// GROUP NUMBER: 11
//
// MEMBERS:
//   - Joshua Smith,    SMTJOS022
//   - Ebrahim Bhyat,   BHYEBR002
//   - Tlangalani Tembe, TMBTLA001

`timescale 1ns / 1ps

`define WORDWIDTH 16
`define INSTRUCTION_DEPTH 16
`define DATA_DEPTH 8
`define SIM_TIME 1

InstructionMemory.v
// =========================================================================
// Practical 4: StarCore-1 — Single-Cycle Processor in Verilog
// =========================================================================
//
// GROUP NUMBER: 11
//
// MEMBERS:
//   - Joshua Smith,    SMTJOS022
//   - Ebrahim Bhyat,   BHYEBR002
//   - Tlangalani Tembe, TMBTLA001

`include "Parameter.v"

module InstructionMemory(
    input [`WORDWIDTH-1:0] pc,
    output [`WORDWIDTH-1:0] instruction

    
);
    reg [`WORDWIDTH-1:0] imem [`INSTRUCTION_DEPTH-1:0];

    initial begin
        $readmemb("test/test.prog", imem);
    end

    assign instruction = imem[pc[4:1]];


endmodule

InstructionMemory_tb.v
`timescale 1ns / 1ps
`include "Parameter.v"
`include "InstructionMemory.v" 

// iverilog -Wall -o imem_sim InstructionMemory_tb.v && ./imem_sim && gtkwave imem_waves.vcd &

module InstructionMemory_tb;

    reg  [`WORDWIDTH-1:0] pc;
    wire [`WORDWIDTH-1:0] instruction;

    InstructionMemory uut (
        .pc(pc),
        .instruction(instruction)
    );

    integer i;

    initial begin
        // Setup waveform dumping for GTKWave
        $dumpfile("imem_waves.vcd");
        $dumpvars(0, InstructionMemory_tb);

        // Dumping memory array in gtkwave for debug
        $dumpvars(0, uut.imem[0]);
        $dumpvars(0, uut.imem[1]);
        $dumpvars(0, uut.imem[2]);
        $dumpvars(0, uut.imem[3]);
        $dumpvars(0, uut.imem[4]);
        $dumpvars(0, uut.imem[5]);
        $dumpvars(0, uut.imem[6]);
        $dumpvars(0, uut.imem[7]);
        $dumpvars(0, uut.imem[8]);
        $dumpvars(0, uut.imem[9]);
        $dumpvars(0, uut.imem[10]);
        $dumpvars(0, uut.imem[11]);
        $dumpvars(0, uut.imem[12]);
        $dumpvars(0, uut.imem[13]);
        $dumpvars(0, uut.imem[14]);
        $dumpvars(0, uut.imem[15]);

        $display("--- Starting Instruction Memory Test ---");

        // Loop through all 16 valid instruction addresses (0, 2, 4 ... 30)
        for (i = 0; i < 16; i = i + 1) begin
            pc = i * 2;  // PC increments by 2
            #10;         // Wait 10ns for the combinational logic to fetch the data
            
            // Print the results to the terminal
            $display("Time: %0t | PC: %02d (0x%04h) | Fetched Instruction: %4h", $time, pc, pc, instruction);
        end

        #20;
        $display("--- Instruction Memory Test Complete ---");
        $finish;
    end

endmodule

imem_waves.vcd
$date
	Sat Apr 25 21:58:05 2026
$end
$version
	Icarus Verilog
$end
$timescale
	1ps
$end
$scope module InstructionMemory_tb $end
$var wire 16 ! instruction [15:0] $end
$var reg 16 " pc [15:0] $end
$var integer 32 # i [31:0] $end
$scope module uut $end
$var wire 16 $ instruction [15:0] $end
$var wire 16 % pc [15:0] $end
$upscope $end
$upscope $end
$scope module InstructionMemory_tb $end
$scope module uut $end
$var reg 16 & \imem[0] [15:0] $end
$upscope $end
$upscope $end
$scope module InstructionMemory_tb $end
$scope module uut $end
$var reg 16 ' \imem[1] [15:0] $end
$upscope $end
$upscope $end
$scope module InstructionMemory_tb $end
$scope module uut $end
$var reg 16 ( \imem[2] [15:0] $end
$upscope $end
$upscope $end
$scope module InstructionMemory_tb $end
$scope module uut $end
$var reg 16 ) \imem[3] [15:0] $end
$upscope $end
$upscope $end
$scope module InstructionMemory_tb $end
$scope module uut $end
$var reg 16 * \imem[4] [15:0] $end
$upscope $end
$upscope $end
$scope module InstructionMemory_tb $end
$scope module uut $end
$var reg 16 + \imem[5] [15:0] $end
$upscope $end
$upscope $end
$scope module InstructionMemory_tb $end
$scope module uut $end
$var reg 16 , \imem[6] [15:0] $end
$upscope $end
$upscope $end
$scope module InstructionMemory_tb $end
$scope module uut $end
$var reg 16 - \imem[7] [15:0] $end
$upscope $end
$upscope $end
$scope module InstructionMemory_tb $end
$scope module uut $end
$var reg 16 . \imem[8] [15:0] $end
$upscope $end
$upscope $end
$scope module InstructionMemory_tb $end
$scope module uut $end
$var reg 16 / \imem[9] [15:0] $end
$upscope $end
$upscope $end
$scope module InstructionMemory_tb $end
$scope module uut $end
$var reg 16 0 \imem[10] [15:0] $end
$upscope $end
$upscope $end
$scope module InstructionMemory_tb $end
$scope module uut $end
$var reg 16 1 \imem[11] [15:0] $end
$upscope $end
$upscope $end
$scope module InstructionMemory_tb $end
$scope module uut $end
$var reg 16 2 \imem[12] [15:0] $end
$upscope $end
$upscope $end
$scope module InstructionMemory_tb $end
$scope module uut $end
$var reg 16 3 \imem[13] [15:0] $end
$upscope $end
$upscope $end
$scope module InstructionMemory_tb $end
$scope module uut $end
$var reg 16 4 \imem[14] [15:0] $end
$upscope $end
$upscope $end
$scope module InstructionMemory_tb $end
$scope module uut $end
$var reg 16 5 \imem[15] [15:0] $end
$upscope $end
$upscope $end
$enddefinitions $end
$comment Show the parameter values. $end
$dumpall
$end
#0
$dumpvars
bx 5
b0 4
b0 3
b0 2
b1101000000000000 1
b1100000001000000 0
b1011000001000001 /
b10000000000000 .
b1001000001010000 -
b1000000001010000 ,
b111000001010000 +
b11000001010000 *
b1001010000010 )
b10001010010000 (
b1000001 '
b10000000 &
b0 %
b10000000 $
b0 #
b0 "
b10000000 !
$end
#10000
b1000001 !
b1000001 $
b10 "
b10 %
b1 #
#20000
b10001010010000 !
b10001010010000 $
b100 "
b100 %
b10 #
#30000
b1001010000010 !
b1001010000010 $
b110 "
b110 %
b11 #
#40000
b11000001010000 !
b11000001010000 $
b1000 "
b1000 %
b100 #
#50000
b111000001010000 !
b111000001010000 $
b1010 "
b1010 %
b101 #
#60000
b1000000001010000 !
b1000000001010000 $
b1100 "
b1100 %
b110 #
#70000
b1001000001010000 !
b1001000001010000 $
b1110 "
b1110 %
b111 #
#80000
b10000000000000 !
b10000000000000 $
b10000 "
b10000 %
b1000 #
#90000
b1011000001000001 !
b1011000001000001 $
b10010 "
b10010 %
b1001 #
#100000
b1100000001000000 !
b1100000001000000 $
b10100 "
b10100 %
b1010 #
#110000
b1101000000000000 !
b1101000000000000 $
b10110 "
b10110 %
b1011 #
#120000
b0 !
b0 $
b11000 "
b11000 %
b1100 #
#130000
b11010 "
b11010 %
b1101 #
#140000
b11100 "
b11100 %
b1110 #
#150000
bx !
bx $
b11110 "
b11110 %
b1111 #
#160000
b10000 #
