Parameter.v
// =========================================================================
// Practical 4: StarCore-1 — Single-Cycle Processor in Verilog
// =========================================================================
//
// GROUP NUMBER: 11
//
// MEMBERS:
//   - Joshua Smith,    SMTJOS022
//   - Ebrahim Bhyat,   BHYEBR002
//   - Tlangalani Tembe, TMBTLA001

`timescale 1ns / 1ps

`define WORDWIDTH 16
`define INSTRUCTION_DEPTH 16
`define DATA_DEPTH 8
`define SIM_TIME 1

ControlUnit.v
// =========================================================================
// Practical 4: StarCore-1 — Single-Cycle Processor in Verilog
// =========================================================================
//
// GROUP NUMBER: 11
//
// MEMBERS:
//   - Joshua Smith,    SMTJOS022
//   - Ebrahim Bhyat,   BHYEBR002
//   - Tlangalani Tembe, TMBTLA001

`include "Parameter.v"

module ControlUnit (
    input [3:0] opcode,

    output reg RegDst,
    output reg ALUsrc,
    output reg MemToReg,
    output reg RegWrite,
    output reg MemRd,
    output reg MemWr,
    output reg Branch,
    output reg [1:0] ALUOp,
    output reg Jump,
    output reg CopEn    // CRU co-processor enable (opcode 1010)

);

    always @(*) begin
        // Default values
        RegDst   = 1'b0;
        ALUsrc   = 1'b0;
        MemToReg = 1'b0;
        RegWrite = 1'b0;
        MemRd    = 1'b0;
        MemWr    = 1'b0;
        Branch   = 1'b0;
        ALUOp    = 2'b00;
        Jump     = 1'b0;
        CopEn    = 1'b0;

        case (opcode)
            4'b0000: begin   // OP = 0, LD I-Type Instruction 
                RegDst = 1'b0;
                ALUsrc = 1'b1;
                MemToReg = 1'b1;
                RegWrite = 1'b1;
                MemRd = 1'b1;
                MemWr = 1'b0;
                Branch = 1'b0;
                ALUOp = 2'b10;
                Jump = 1'b0;
                
            end
            4'b0001: begin   // OP = 1, STR I-Type Instruction
                RegDst = 1'b0;
                ALUsrc = 1'b1;
                MemToReg = 1'b0;
                RegWrite = 1'b0;
                MemRd = 1'b0;
                MemWr = 1'b1;
                Branch = 1'b0;
                ALUOp = 2'b10;
                Jump = 1'b0;
                
            end
            4'b0010: begin   // OP = 2, ADD R-Type Instruction
                RegDst = 1'b1;
                ALUsrc = 1'b0;
                MemToReg = 1'b0;
                RegWrite = 1'b1;
                MemRd = 1'b0;
                MemWr = 1'b0;
                Branch = 1'b0;
                ALUOp = 2'b00;
                Jump = 1'b0;
            end
            4'b0011: begin   // OP = 3, SUB R-Type Instruction
                RegDst = 1'b1;
                ALUsrc = 1'b0;
                MemToReg = 1'b0;
                RegWrite = 1'b1;
                MemRd = 1'b0;
                MemWr = 1'b0;
                Branch = 1'b0;
                ALUOp = 2'b00;
                Jump = 1'b0;
            end
            4'b0100: begin   // OP = 4, INV R-Type Instruction
                RegDst = 1'b1;
                ALUsrc = 1'b0;
                MemToReg = 1'b0;
                RegWrite = 1'b1;
                MemRd = 1'b0;
                MemWr = 1'b0;
                Branch = 1'b0;
                ALUOp = 2'b00;
                Jump = 1'b0;
            end
            4'b0101: begin   // OP = 5, SHL R-Type Instruction
                RegDst = 1'b1;
                ALUsrc = 1'b0;
                MemToReg = 1'b0;
                RegWrite = 1'b1;
                MemRd = 1'b0;
                MemWr = 1'b0;
                Branch = 1'b0;
                ALUOp = 2'b00;
                Jump = 1'b0;
            end
            4'b0110: begin   // OP = 6, SHR R-Type Instruction
                RegDst = 1'b1;
                ALUsrc = 1'b0;
                MemToReg = 1'b0;
                RegWrite = 1'b1;
                MemRd = 1'b0;
                MemWr = 1'b0;
                Branch = 1'b0;
                ALUOp = 2'b00;
                Jump = 1'b0;
            end
            4'b0111: begin   // OP = 7, AND R-Type Instruction
                RegDst = 1'b1;
                ALUsrc = 1'b0;
                MemToReg = 1'b0;
                RegWrite = 1'b1;
                MemRd = 1'b0;
                MemWr = 1'b0;
                Branch = 1'b0;
                ALUOp = 2'b00;
                Jump = 1'b0;
            end
            4'b1000: begin   // OP = 8, OR R-Type Instruction
                RegDst = 1'b1;
                ALUsrc = 1'b0;
                MemToReg = 1'b0;
                RegWrite = 1'b1;
                MemRd = 1'b0;
                MemWr = 1'b0;
                Branch = 1'b0;
                ALUOp = 2'b00;
                Jump = 1'b0;
            end
            4'b1001: begin   // OP = 9, SLT R-Type Instruction
                RegDst = 1'b1;
                ALUsrc = 1'b0;
                MemToReg = 1'b0;
                RegWrite = 1'b1;
                MemRd = 1'b0;
                MemWr = 1'b0;
                Branch = 1'b0;
                ALUOp = 2'b00;
                Jump = 1'b0;
            end
            4'b1010: begin   // OP = 10, COP — Coordinate Rotation Unit
                RegDst   = 1'b0; // WS from inst[8:6] (I-type field)
                ALUsrc   = 1'b0;
                MemToReg = 1'b0;
                RegWrite = 1'b0; // write-back gated by cru_done in Datapath
                MemRd    = 1'b0;
                MemWr    = 1'b0;
                Branch   = 1'b0;
                ALUOp    = 2'b00;
                Jump     = 1'b0;
                CopEn    = 1'b1; // signal Datapath to run CRU
            end
            4'b1011: begin   // OP = 11, BEQ
                RegDst = 1'b0;
                ALUsrc = 1'b0;
                MemToReg = 1'b0;
                RegWrite = 1'b0;
                MemRd = 1'b0;
                MemWr = 1'b0;
                Branch = 1'b1;
                ALUOp = 2'b01;
                Jump = 1'b0;

            end
            4'b1100: begin   // OP = 12, BNE
                RegDst = 1'b0;
                ALUsrc = 1'b0;
                MemToReg = 1'b0;
                RegWrite = 1'b0;
                MemRd = 1'b0;
                MemWr = 1'b0;
                Branch = 1'b1;
                ALUOp = 2'b01;
                Jump = 1'b0;
            end
            4'b1101: begin   // OP = 13, JMP
                RegDst = 1'b0;
                ALUsrc = 1'b0;
                MemToReg = 1'b0;
                RegWrite = 1'b0;
                MemRd = 1'b0;
                MemWr = 1'b0;
                Branch = 1'b0;
                ALUOp = 2'b00;
                Jump = 1'b1;

            end
            4'b1110: begin   // OP = 14
                RegDst = 1'b0;
                ALUsrc = 1'b0;
                MemToReg = 1'b0;
                RegWrite = 1'b0;
                MemRd = 1'b0;
                MemWr = 1'b0;
                Branch = 1'b0;
                ALUOp = 2'b00;
                Jump = 1'b0;
            end
            4'b1111: begin   // OP = 15
                RegDst = 1'b0;
                ALUsrc = 1'b0;
                MemToReg = 1'b0;
                RegWrite = 1'b0;
                MemRd = 1'b0;
                MemWr = 1'b0;
                Branch = 1'b0;
                ALUOp = 2'b00;
                Jump = 1'b0;
            end



        default: ;

        endcase
    end

endmodule

test/ControlUnit_tb.v
`timescale 1ns / 1ps
`include "../src/Parameter.v"
`include "../src/ControlUnit.v"

module ControlUnit_tb;

    reg [3:0] opcode;

    wire RegDst;
    wire ALUsrc;
    wire MemToReg;
    wire RegWrite;
    wire MemRd;
    wire MemWr;
    wire Branch;
    wire [1:0] ALUOp;
    wire Jump;
    wire CopEn;

    ControlUnit uut (
        .opcode(opcode),
        .RegDst(RegDst),
        .ALUsrc(ALUsrc),
        .MemToReg(MemToReg),
        .RegWrite(RegWrite),
        .MemRd(MemRd),
        .MemWr(MemWr),
        .Branch(Branch),
        .ALUOp(ALUOp),
        .Jump(Jump),
        .CopEn(CopEn)
    );

    integer i;

    initial begin
        $dumpfile("waves/control_unit_waves.vcd");
        $dumpvars(0, ControlUnit_tb);

        $display("--- Starting Control Unit Tests ---");
        $display("OPC | RegDst ALUsrc MemToReg RegWrite MemRd MemWr Branch ALUOp Jump CopEn");
        $display("--------------------------------------------------------------------------");

        for (i = 0; i < 16; i = i + 1) begin
            opcode = i;
            #10;
            $display(" %2h |   %b      %b       %b        %b       %b     %b      %b      %b    %b     %b",
                     opcode, RegDst, ALUsrc, MemToReg, RegWrite, MemRd, MemWr, Branch, ALUOp, Jump, CopEn);

            if (opcode == 4'b1010) begin
                if ({RegDst, ALUsrc, MemToReg, RegWrite, MemRd, MemWr, Branch, ALUOp, Jump} !== 10'b0)
                    $display(">> FAIL: COP opcode did NOT produce all zeros on standard signals!");
                else if (CopEn !== 1'b1)
                    $display(">> FAIL: COP opcode did not assert CopEn!");
                else
                    $display(">> PASS: COP opcode correctly asserts CopEn, all other signals zero.");
            end
        end

        #20;
        $display("--- Control Unit Tests Complete ---");
        $finish;
    end

endmodule

waves/control_unit_waves.vcd
$date
	Mon May 18 09:35:14 2026
$end
$version
	Icarus Verilog
$end
$timescale
	1ps
$end
$scope module ControlUnit_tb $end
$var wire 1 ! RegWrite $end
$var wire 1 " RegDst $end
$var wire 1 # MemWr $end
$var wire 1 $ MemToReg $end
$var wire 1 % MemRd $end
$var wire 1 & Jump $end
$var wire 1 ' CopEn $end
$var wire 1 ( Branch $end
$var wire 1 ) ALUsrc $end
$var wire 2 * ALUOp [1:0] $end
$var reg 4 + opcode [3:0] $end
$var integer 32 , i [31:0] $end
$scope module uut $end
$var wire 4 - opcode [3:0] $end
$var reg 2 . ALUOp [1:0] $end
$var reg 1 ) ALUsrc $end
$var reg 1 ( Branch $end
$var reg 1 ' CopEn $end
$var reg 1 & Jump $end
$var reg 1 % MemRd $end
$var reg 1 $ MemToReg $end
$var reg 1 # MemWr $end
$var reg 1 " RegDst $end
$var reg 1 ! RegWrite $end
$upscope $end
$upscope $end
$enddefinitions $end
$comment Show the parameter values. $end
$dumpall
$end
#0
$dumpvars
b10 .
b0 -
b0 ,
b0 +
b10 *
1)
0(
0'
0&
1%
1$
0#
0"
1!
$end
#10000
1#
b10 *
b10 .
0%
0!
0$
1)
b1 +
b1 -
b1 ,
#20000
1!
1"
b0 *
b0 .
0#
0)
b10 +
b10 -
b10 ,
#30000
1!
1"
b11 +
b11 -
b11 ,
#40000
1!
1"
b100 +
b100 -
b100 ,
#50000
1!
1"
b101 +
b101 -
b101 ,
#60000
1!
1"
b110 +
b110 -
b110 ,
#70000
1!
1"
b111 +
b111 -
b111 ,
#80000
1!
1"
b1000 +
b1000 -
b1000 ,
#90000
1!
1"
b1001 +
b1001 -
b1001 ,
#100000
1'
0!
0"
b1010 +
b1010 -
b1010 ,
#110000
b1 *
b1 .
1(
0'
b1011 +
b1011 -
b1011 ,
#120000
b1 *
b1 .
1(
b1100 +
b1100 -
b1100 ,
#130000
1&
b0 *
b0 .
0(
b1101 +
b1101 -
b1101 ,
#140000
0&
b1110 +
b1110 -
b1110 ,
#150000
b1111 +
b1111 -
b1111 ,
#160000
b10000 ,
