CRU.v
// =========================================================================
// EEE4120F HPES Project — Coordinate Rotation Unit (CRU)
// CORDIC Co-Processor for StarCore-1
// =========================================================================
//
// GROUP NUMBER: 11
//
// MEMBERS:
//   - Joshua Smith,  SMTJOS022
//   - Ebrahim Bhyat, BHYEBR002
//   - Tlangalani Tembe, TMBTLA001
//
// -------------------------------------------------------------------------
// Algorithm: CORDIC rotation mode (15 iterations)
//
// TWO fixed-point formats are used:
//
//   Angle input  — Q3.13  (scale = 2^13 = 8192)
//     1 sign bit, 2 integer bits, 13 fractional bits. Range: [-4.0, ~4.0]
//     Covers the full ±π range:  π × 8192 = 25737  (<32767 ✓)
//     Caller encodes:  angle_in = round(angle_radians × 8192)
//
//   Cos/sin output  — Q2.14  (scale = 2^14 = 16384)
//     1 sign bit, 1 integer bit, 14 fractional bits. Range: [-2.0, ~2.0]
//     Output values lie in [-1, 1]:  ±1.0 → ±16384
//
// Quadrant extension:
//   CORDIC converges for |z| < π/2.  Angles in (-π, -π/2] or [π/2, π)
//   are folded by ±π before the CORDIC loop, and both outputs are negated
//   on the way out:
//       cos(θ ± π) = -cos(θ)    sin(θ ± π) = -sin(θ)
//
//   The folded angle (Q3.13) is converted to Q2.14 via a left-shift-by-1
//   before being loaded into z.  After folding, |z_Q3_13| ≤ 12868,
//   so z_Q2_14 = z_Q3_13 << 1 ≤ 25736 — safely within 16-bit signed. ✓
//
// Interface:
//   - Assert start=1 while CRU is idle to begin a computation.
//   - busy goes high on the cycle start is accepted.
//   - done pulses high for exactly one cycle when results are valid.
//   - Total latency: 17 clock cycles  (1 latch + 15 CORDIC + 1 output).
// =========================================================================

`timescale 1ns / 1ps

module CRU (
    input  wire                  clk,
    input  wire                  reset,
    input  wire                  start,       // trigger: high while idle to begin
    input  wire signed [15:0]    angle_in,    // Q3.13: angle in radians × 8192

    output reg  signed [15:0]    cos_out,     // Q2.14: cosine result × 16384
    output reg  signed [15:0]    sin_out,     // Q2.14: sine result  × 16384
    output reg                   busy,        // high during computation
    output reg                   done         // high for one cycle when valid
);

    // -----------------------------------------------------------------------
    // Constants
    // -----------------------------------------------------------------------
    // Q3.13 angle constants (scale = 8192)
    localparam signed [15:0] HALF_PI_Q3_13 = 16'sd12868; // π/2 × 8192
    localparam signed [15:0] PI_Q3_13      = 16'sd25737; // π   × 8192

    // CORDIC gain pre-compensation (Q2.14, scale = 16384):
    //   x_init = (1 / K_15) × 16384,  K_15 ≈ 1.6468  →  1/K_15 ≈ 0.6073
    //   round(0.6073 × 16384) = 9949
    localparam signed [15:0] K_INIT = 16'sd9949;

    // atan(2^-i) × 16384 for i = 0..14   (Q2.14, matches internal z format)
    reg signed [15:0] atan_lut [0:14];
    initial begin
        atan_lut[0]  = 16'sd12868; // atan(2^0)  = π/4  = 0.7854 rad
        atan_lut[1]  = 16'sd7596;  // atan(2^-1)        = 0.4636 rad
        atan_lut[2]  = 16'sd4014;  // atan(2^-2)        = 0.2450 rad
        atan_lut[3]  = 16'sd2037;  // atan(2^-3)        = 0.1244 rad
        atan_lut[4]  = 16'sd1022;  // atan(2^-4)        = 0.0624 rad
        atan_lut[5]  = 16'sd512;   // atan(2^-5)        = 0.0312 rad
        atan_lut[6]  = 16'sd256;   // atan(2^-6)
        atan_lut[7]  = 16'sd128;   // atan(2^-7)
        atan_lut[8]  = 16'sd64;    // atan(2^-8)
        atan_lut[9]  = 16'sd32;    // atan(2^-9)
        atan_lut[10] = 16'sd16;    // atan(2^-10)
        atan_lut[11] = 16'sd8;     // atan(2^-11)
        atan_lut[12] = 16'sd4;     // atan(2^-12)
        atan_lut[13] = 16'sd2;     // atan(2^-13)
        atan_lut[14] = 16'sd1;     // atan(2^-14)
    end

    // -----------------------------------------------------------------------
    // FSM states
    // -----------------------------------------------------------------------
    localparam [1:0] IDLE    = 2'd0;
    localparam [1:0] RUNNING = 2'd1;
    localparam [1:0] DONE    = 2'd2;

    reg [1:0]         state;
    reg [3:0]         iter;    // iteration counter 0..14
    reg               negate;  // quadrant compensation flag

    // CORDIC working registers (Q2.14, signed)
    reg signed [15:0] x, y, z;

    // -----------------------------------------------------------------------
    // CORDIC FSM
    // -----------------------------------------------------------------------
    always @(posedge clk) begin
        if (reset) begin
            state   <= IDLE;
            busy    <= 1'b0;
            done    <= 1'b0;
            iter    <= 4'd0;
            negate  <= 1'b0;
            cos_out <= 16'sd0;
            sin_out <= 16'sd0;
            x       <= 16'sd0;
            y       <= 16'sd0;
            z       <= 16'sd0;

        end else begin
            case (state)

                // ------------------------------------------------------------
                // IDLE: wait for start.
                //
                // Quadrant fold (Q3.13 arithmetic, no overflow risk):
                //   angle in [π/2, π)  → subtract π, set negate
                //   angle in (-π, -π/2] → add    π, set negate
                //   otherwise           → use directly
                //
                // Then convert folded Q3.13 angle to Q2.14 via << 1 for z.
                //   Folded range: |z_Q3_13| ≤ 12868
                //   After << 1:   |z_Q2_14| ≤ 25736  (fits in 16-bit signed ✓)
                // ------------------------------------------------------------
                IDLE: begin
                    done <= 1'b0;
                    if (start) begin
                        busy <= 1'b1;
                        iter <= 4'd0;
                        x    <= K_INIT;
                        y    <= 16'sd0;

                        if (angle_in >= HALF_PI_Q3_13) begin
                            // Q2 angle: fold into (-π/2, 0], negate outputs
                            z      <= (angle_in - PI_Q3_13) <<< 1;
                            negate <= 1'b1;
                        end else if (angle_in <= -HALF_PI_Q3_13) begin
                            // Q3 angle: fold into [0, π/2), negate outputs
                            z      <= (angle_in + PI_Q3_13) <<< 1;
                            negate <= 1'b1;
                        end else begin
                            // Q1/Q4 angle: already in convergence range
                            z      <= angle_in <<< 1;
                            negate <= 1'b0;
                        end

                        state <= RUNNING;
                    end
                end

                // ------------------------------------------------------------
                // RUNNING: one CORDIC micro-rotation per clock cycle.
                //
                //   d = sign(z):
                //     x[i+1] = x[i] − d × (y[i] >>> i)
                //     y[i+1] = y[i] + d × (x[i] >>> i)
                //     z[i+1] = z[i] − d × atan_lut[i]
                //
                //   >>> is arithmetic right-shift (sign-extending).
                //   Non-blocking assignments ensure RHS uses pre-update values.
                // ------------------------------------------------------------
                RUNNING: begin
                    if (z >= 16'sd0) begin
                        x <= x - (y >>> iter);
                        y <= y + (x >>> iter);
                        z <= z - atan_lut[iter];
                    end else begin
                        x <= x + (y >>> iter);
                        y <= y - (x >>> iter);
                        z <= z + atan_lut[iter];
                    end

                    if (iter == 4'd14)
                        state <= DONE;
                    else
                        iter <= iter + 4'd1;
                end

                // ------------------------------------------------------------
                // DONE: apply quadrant negation, latch outputs, pulse done.
                // ------------------------------------------------------------
                DONE: begin
                    busy    <= 1'b0;
                    done    <= 1'b1;
                    cos_out <= negate ? -x : x;
                    sin_out <= negate ? -y : y;
                    state   <= IDLE;
                end

                default: state <= IDLE;

            endcase
        end
    end

endmodule

CRU_tb.v
// =========================================================================
// EEE4120F HPES Project — CRU Testbench
// =========================================================================
//
// GROUP NUMBER: 11
//
// MEMBERS:
//   - Joshua Smith,  SMTJOS022
//   - Ebrahim Bhyat, BHYEBR002
//   - Tlangalani Tembe, TMBTLA001
//
// -------------------------------------------------------------------------
// Verifies the CORDIC engine across the full ±π range.
//
// Angle input format:  Q3.13  (scale = 8192)
//   angle_in = round(angle_radians × 8192)
//
// Output format:  Q2.14  (scale = 16384)
//   result = round(cos_or_sin × 16384)
//
// Pass criterion: |result - expected| <= 8  (~0.05% of full scale)
// 15-iteration Q2.14 CORDIC accumulates up to ~5 LSBs of truncation error
// across the shift-add chain; threshold of 8 gives comfortable margin.
// =========================================================================

`timescale 1ns / 1ps

module CRU_tb;

    // -----------------------------------------------------------------------
    // DUT signals
    // -----------------------------------------------------------------------
    reg         clk;
    reg         reset;
    reg         start;
    reg  signed [15:0] angle_in;

    wire signed [15:0] cos_out;
    wire signed [15:0] sin_out;
    wire               busy;
    wire               done;

    // -----------------------------------------------------------------------
    // DUT instantiation
    // -----------------------------------------------------------------------
    CRU uut (
        .clk      (clk),
        .reset    (reset),
        .start    (start),
        .angle_in (angle_in),
        .cos_out  (cos_out),
        .sin_out  (sin_out),
        .busy     (busy),
        .done     (done)
    );

    // -----------------------------------------------------------------------
    // Clock: 10 ns period
    // -----------------------------------------------------------------------
    initial clk = 0;
    always #5 clk = ~clk;

    // -----------------------------------------------------------------------
    // Helper task: run one CORDIC computation and report results
    // -----------------------------------------------------------------------
    integer pass_count;
    integer fail_count;

    task run_test;
        input signed [15:0] angle;      // Q3.13
        input signed [15:0] exp_cos;    // Q2.14
        input signed [15:0] exp_sin;    // Q2.14
        input [255:0]        label;

        integer cos_err, sin_err;
        integer timeout;
        begin
            @(negedge clk);
            angle_in = angle;
            start    = 1'b1;
            @(posedge clk);
            #1;
            start = 1'b0;

            timeout = 0;
            while (!done && timeout < 30) begin
                @(posedge clk);
                #1;
                timeout = timeout + 1;
            end

            if (timeout >= 30) begin
                $display("TIMEOUT  [%s]  angle=%0d", label, angle);
                fail_count = fail_count + 1;
            end else begin
                cos_err = cos_out - exp_cos;
                sin_err = sin_out - exp_sin;
                if (cos_err < 0) cos_err = -cos_err;
                if (sin_err < 0) sin_err = -sin_err;

                if (cos_err <= 8 && sin_err <= 8) begin
                    $display("PASS  [%s]  cos=%6d (exp %6d)  sin=%6d (exp %6d)",
                             label, cos_out, exp_cos, sin_out, exp_sin);
                    pass_count = pass_count + 1;
                end else begin
                    $display("FAIL  [%s]  cos=%6d (exp %6d, err=%0d)  sin=%6d (exp %6d, err=%0d)",
                             label, cos_out, exp_cos, cos_err, sin_out, exp_sin, sin_err);
                    fail_count = fail_count + 1;
                end
            end

            @(negedge clk);
        end
    endtask

    // -----------------------------------------------------------------------
    // Stimulus
    // -----------------------------------------------------------------------
    // Q3.13 angle input:  round(radians × 8192)
    // Q2.14 expected out: round(value   × 16384)
    //
    // Acute  (Q1, no fold):
    //   0        →  angle=0,      cos=16384,  sin=0
    //   π/6      →  angle=4291,   cos=14189,  sin=8192
    //   π/4      →  angle=6434,   cos=11585,  sin=11585
    //   π/3      →  angle=8579,   cos=8192,   sin=14189
    //
    // Obtuse (Q2, fold by −π):
    //   2π/3     →  angle=17157,  cos=-8192,  sin=14189
    //   3π/4     →  angle=19302,  cos=-11585, sin=11585
    //   5π/6     →  angle=21446,  cos=-14189, sin=8192
    //
    // Boundary:
    //   π/2      →  angle=12868,  cos=0,      sin=16384
    //   π        →  angle=25737,  cos=-16384, sin=0
    //
    // Negative (Q4 and Q3):
    //   -π/4     →  angle=-6434,  cos=11585,  sin=-11585
    //   -π/2     →  angle=-12868, cos=0,      sin=-16384
    //   -3π/4    →  angle=-19302, cos=-11585, sin=-11585

    initial begin
        $dumpfile("../waves/cru_tb.vcd");
        $dumpvars(0, CRU_tb);

        pass_count = 0;
        fail_count = 0;
        start      = 0;
        angle_in   = 0;

        reset = 1;
        repeat(3) @(posedge clk);
        reset = 0;
        @(negedge clk);

        $display("=======================================================");
        $display("   CRU CORDIC Testbench — Full ±pi Range (Q3.13 in)   ");
        $display("=======================================================");
        $display("  Angle in: Q3.13 (×8192).  Out: Q2.14 (×16384).");
        $display("  Pass threshold: |err| <= 8 (~0.05%%)");
        $display("-------------------------------------------------------");
        $display("  --- Acute angles (no quadrant fold) ---");

        run_test(16'sd0,      16'sd16384, 16'sd0,     "theta = 0       ");
        run_test(16'sd4291,   16'sd14189, 16'sd8192,  "theta = pi/6    ");
        run_test(16'sd6434,   16'sd11585, 16'sd11585, "theta = pi/4    ");
        run_test(16'sd8579,   16'sd8192,  16'sd14189, "theta = pi/3    ");

        $display("  --- Boundary angles ---");

        run_test(16'sd12868,  16'sd0,     16'sd16384, "theta = pi/2    ");
        run_test(16'sd25737, -16'sd16384, 16'sd0,     "theta = pi      ");

        $display("  --- Obtuse angles (quadrant fold applied) ---");

        run_test(16'sd17157, -16'sd8192,  16'sd14189, "theta = 2pi/3   ");
        run_test(16'sd19302, -16'sd11585, 16'sd11585, "theta = 3pi/4   ");
        run_test(16'sd21446, -16'sd14189, 16'sd8192,  "theta = 5pi/6   ");

        $display("  --- Negative angles ---");

        run_test(-16'sd6434,  16'sd11585,-16'sd11585, "theta = -pi/4   ");
        run_test(-16'sd12868, 16'sd0,    -16'sd16384, "theta = -pi/2   ");
        run_test(-16'sd19302,-16'sd11585,-16'sd11585, "theta = -3pi/4  ");

        $display("  --- Back-to-back IDLE recovery ---");

        run_test(16'sd0,      16'sd16384, 16'sd0,     "theta = 0 again ");

        $display("-------------------------------------------------------");
        $display("  Results: %0d passed, %0d failed", pass_count, fail_count);
        $display("=======================================================");
        $finish;
    end

endmodule

waves/cru_tb.vcd
$date
	Wed May 20 21:37:23 2026
$end
$version
	Icarus Verilog
$end
$timescale
	1ps
$end
$scope module CRU_tb $end
$var wire 16 ! sin_out [15:0] $end
$var wire 1 " done $end
$var wire 16 # cos_out [15:0] $end
$var wire 1 $ busy $end
$var reg 16 % angle_in [15:0] $end
$var reg 1 & clk $end
$var reg 1 ' reset $end
$var reg 1 ( start $end
$var integer 32 ) fail_count [31:0] $end
$var integer 32 * pass_count [31:0] $end
$scope module uut $end
$var wire 16 + angle_in [15:0] $end
$var wire 1 & clk $end
$var wire 1 ' reset $end
$var wire 1 ( start $end
$var parameter 2 , DONE $end
$var parameter 16 - HALF_PI_Q3_13 $end
$var parameter 2 . IDLE $end
$var parameter 16 / K_INIT $end
$var parameter 16 0 PI_Q3_13 $end
$var parameter 2 1 RUNNING $end
$var reg 1 $ busy $end
$var reg 16 2 cos_out [15:0] $end
$var reg 1 " done $end
$var reg 4 3 iter [3:0] $end
$var reg 1 4 negate $end
$var reg 16 5 sin_out [15:0] $end
$var reg 2 6 state [1:0] $end
$var reg 16 7 x [15:0] $end
$var reg 16 8 y [15:0] $end
$var reg 16 9 z [15:0] $end
$upscope $end
$scope task run_test $end
$var reg 16 : angle [15:0] $end
$var reg 16 ; exp_cos [15:0] $end
$var reg 16 < exp_sin [15:0] $end
$var reg 256 = label [255:0] $end
$var integer 32 > cos_err [31:0] $end
$var integer 32 ? sin_err [31:0] $end
$var integer 32 @ timeout [31:0] $end
$upscope $end
$upscope $end
$enddefinitions $end
$comment Show the parameter values. $end
$dumpall
b1 1
b110010010001001 0
b10011011011101 /
b0 .
b11001001000100 -
b10 ,
$end
#0
$dumpvars
bx @
bx ?
bx >
bx =
bx <
bx ;
bx :
bx 9
bx 8
bx 7
bx 6
bx 5
x4
bx 3
bx 2
b0 +
b0 *
b0 )
0(
1'
0&
b0 %
x$
bx #
x"
bx !
$end
#5000
b0 9
b0 8
b0 7
b0 !
b0 5
b0 #
b0 2
04
b0 3
0"
0$
b0 6
1&
#10000
0&
#15000
1&
#20000
0&
#25000
0'
1&
#30000
b1110100011010000110010101110100011000010010000000111101001000000010000000100000001100000010000001100100011001010110011100100000 =
b0 <
b100000000000000 ;
b0 :
0&
#35000
1&
#40000
1(
0&
#45000
b1 6
b10011011011101 7
1$
1&
#46000
b0 @
0(
#50000
0&
#55000
b1 3
b1100110110111100 9
b10011011011101 8
1&
#56000
b1 @
#60000
0&
#65000
b10 3
b1110101101101000 9
b1001101101111 8
b11101001001011 7
1&
#66000
b10 @
#70000
0&
#75000
b11 3
b1111101100010110 9
b10011011101 8
b11111100100110 7
1&
#76000
b11 @
#80000
0&
#85000
b100 3
b1100001011 9
b1111110011111001 8
b11111111000001 7
1&
#86000
b100 @
#90000
0&
#95000
b101 3
b1111111100001101 9
b11110101 8
b11111111110010 7
1&
#96000
b101 @
#100000
0&
#105000
b110 3
b100001101 9
b1111111011110110 8
b11111111111001 7
1&
#106000
b110 @
#110000
0&
#115000
b111 3
b1101 9
b1111111111110101 8
b11111111111110 7
1&
#116000
b111 @
#120000
0&
#125000
b1000 3
b1111111110001101 9
b1110100 8
b11111111111111 7
1&
#126000
b1000 @
#130000
0&
#135000
b1001 3
b1111111111001101 9
b110101 8
1&
#136000
b1001 @
#140000
0&
#145000
b1010 3
b1111111111101101 9
b10110 8
1&
#146000
b1010 @
#150000
0&
#155000
b1011 3
b1111111111111101 9
b111 8
1&
#156000
b1011 @
#160000
0&
#165000
b1100 3
b101 9
b0 8
1&
#166000
b1100 @
#170000
0&
#175000
b1101 3
b1 9
b11 8
1&
#176000
b1101 @
#180000
0&
#185000
b1110 3
b1111111111111111 9
b100 8
1&
#186000
b1110 @
#190000
0&
#195000
b10 6
b0 9
1&
#196000
b1111 @
#200000
0&
#205000
b0 6
b100 !
b100 5
b11111111111111 #
b11111111111111 2
1"
0$
1&
#206000
b1 *
b100 ?
b1 >
b10000 @
#210000
b1110100011010000110010101110100011000010010000000111101001000000010000000110001001101010010000001100100011001010110011100100000 =
b1000010010000 <
b11110111010010 ;
b100001100001 :
0&
#215000
0"
1&
#220000
1(
b100001100001 %
b100001100001 +
0&
#225000
b1 6
b1000011000010 9
b0 8
b10011011011101 7
b0 3
1$
1&
#226000
b0 @
0(
#230000
0&
#235000
b1 3
b1101111001111110 9
b10011011011101 8
1&
#236000
b1 @
#240000
0&
#245000
b10 3
b1111110000101010 9
b1001101101111 8
b11101001001011 7
1&
#246000
b10 @
#250000
0&
#255000
b11 3
b101111011000 9
b10011011101 8
b11111100100110 7
1&
#256000
b11 @
#260000
0&
#265000
b100 3
b1111100011 9
b110011000001 8
b11111010001011 7
1&
#266000
b100 @
#270000
0&
#275000
b101 3
b1111111111100101 9
b1000010101001 8
b11110110111111 7
1&
#276000
b101 @
#280000
0&
#285000
b110 3
b111100101 9
b111010111100 8
b11111001000100 7
1&
#286000
b110 @
#290000
0&
#295000
b111 3
b11100101 9
b111110110101 8
b11111000001010 7
1&
#296000
b111 @
#300000
0&
#305000
b1000 3
b1100101 9
b1000000110001 8
b11110111101011 7
1&
#306000
b1000 @
#310000
0&
#315000
b1001 3
b100101 9
b1000001101110 8
b11110111011011 7
1&
#316000
b1001 @
#320000
0&
#325000
b1010 3
b101 9
b1000010001100 8
b11110111010011 7
1&
#326000
b1010 @
#330000
0&
#335000
b1011 3
b1111111111110101 9
b1000010011011 8
b11110111001111 7
1&
#336000
b1011 @
#340000
0&
#345000
b1100 3
b1111111111111101 9
b1000010010100 8
b11110111010001 7
1&
#346000
b1100 @
#350000
0&
#355000
b1101 3
b1 9
b1000010010001 8
b11110111010010 7
1&
#356000
b1101 @
#360000
0&
#365000
b1110 3
b1111111111111111 9
b1000010010010 8
1&
#366000
b1110 @
#370000
0&
#375000
b10 6
b0 9
1&
#376000
b1111 @
#380000
0&
#385000
b0 6
b1000010010010 !
b1000010010010 5
b11110111010010 #
b11110111010010 2
1"
0$
1&
#386000
b10 *
b10 ?
b0 >
b10000 @
#390000
b1110100011010000110010101110100011000010010000000111101001000000010000000110011001100000010000001100100011001010110011100100000 =
b10000000000000 <
b11011101101101 ;
b1000011000001 :
0&
#395000
0"
1&
#400000
1(
b1000011000001 %
b1000011000001 +
0&
#405000
b1 6
b10000110000010 9
b0 8
b10011011011101 7
b0 3
1$
1&
#406000
b0 @
0(
#410000
0&
#415000
b1 3
b1110111100111110 9
b10011011011101 8
1&
#416000
b1 @
#420000
0&
#425000
b10 3
b110011101010 9
b1001101101111 8
b11101001001011 7
1&
#426000
b10 @
#430000
0&
#435000
b11 3
b1111110100111100 9
b10001000000001 8
b11010101110000 7
1&
#436000
b11 @
#440000
0&
#445000
b100 3
b10100110001 9
b1101101010011 8
b11100110110000 7
1&
#446000
b100 @
#450000
0&
#455000
b101 3
b100110011 9
b1111011101110 8
b11011111111011 7
1&
#456000
b101 @
#460000
0&
#465000
b110 3
b1111111100110011 9
b10000010101101 8
b11011100000100 7
1&
#466000
b110 @
#470000
0&
#475000
b111 3
b110011 9
b1111111010001 8
b11011110000110 7
1&
#476000
b111 @
#480000
0&
#485000
b1000 3
b1111111110110011 9
b10000001000000 8
b11011101000111 7
1&
#486000
b1000 @
#490000
0&
#495000
b1001 3
b1111111111110011 9
b10000000001001 8
b11011101100111 7
1&
#496000
b1001 @
#500000
0&
#505000
b1010 3
b10011 9
b1111111101110 8
b11011101110111 7
1&
#506000
b1010 @
#510000
0&
#515000
b1011 3
b11 9
b1111111111011 8
b11011101110000 7
1&
#516000
b1011 @
#520000
0&
#525000
b1100 3
b1111111111111011 9
b10000000000001 8
b11011101101101 7
1&
#526000
b1100 @
#530000
0&
#535000
b1101 3
b1111111111111111 9
b1111111111110 8
b11011101101111 7
1&
#536000
b1101 @
#540000
0&
#545000
b1110 3
b1 9
b1111111111101 8
1&
#546000
b1110 @
#550000
0&
#555000
b10 6
b0 9
1&
#556000
b1111 @
#560000
0&
#565000
b0 6
b1111111111101 !
b1111111111101 5
b11011101101111 #
b11011101101111 2
1"
0$
1&
#566000
b11 *
b11 ?
b10 >
b10000 @
#570000
b1110100011010000110010101110100011000010010000000111101001000000010000000110100001101010010000001100100011001010110011100100000 =
b10110101000001 <
b10110101000001 ;
b1100100100010 :
0&
#575000
0"
1&
#580000
1(
b1100100100010 %
b1100100100010 +
0&
#585000
b1 6
b11001001000100 9
b0 8
b10011011011101 7
b0 3
1$
1&
#586000
b0 @
0(
#590000
0&
#595000
b1 3
b0 9
b10011011011101 8
1&
#596000
b1 @
#600000
0&
#605000
b10 3
b1110001001010100 9
b11101001001011 8
b1001101101111 7
1&
#606000
b10 @
#610000
0&
#615000
b11 3
b1111001000000010 9
b11010101110000 8
b10001000000001 7
1&
#616000
b11 @
#620000
0&
#625000
b100 3
b1111100111110111 9
b11000100110000 8
b10100010101111 7
1&
#626000
b100 @
#630000
0&
#635000
b101 3
b1111110111110101 9
b10111010100110 8
b10101111000010 7
1&
#636000
b101 @
#640000
0&
#645000
b110 3
b1111111111110101 9
b10110101001000 8
b10110100110111 7
1&
#646000
b110 @
#650000
0&
#655000
b111 3
b11110101 9
b10110010010100 8
b10110111101100 7
1&
#656000
b111 @
#660000
0&
#665000
b1000 3
b1110101 9
b10110011101111 8
b10110110010011 7
1&
#666000
b1000 @
#670000
0&
#675000
b1001 3
b110101 9
b10110100011100 8
b10110101100111 7
1&
#676000
b1001 @
#680000
0&
#685000
b1010 3
b10101 9
b10110100110010 8
b10110101010001 7
1&
#686000
b1010 @
#690000
0&
#695000
b1011 3
b101 9
b10110100111101 8
b10110101000110 7
1&
#696000
b1011 @
#700000
0&
#705000
b1100 3
b1111111111111101 9
b10110101000010 8
b10110101000001 7
1&
#706000
b1100 @
#710000
0&
#715000
b1101 3
b1 9
b10110101000000 8
b10110101000011 7
1&
#716000
b1101 @
#720000
0&
#725000
b1110 3
b1111111111111111 9
b10110101000001 8
b10110101000010 7
1&
#726000
b1110 @
#730000
0&
#735000
b10 6
b0 9
1&
#736000
b1111 @
#740000
0&
#745000
b0 6
b10110101000001 !
b10110101000001 5
b10110101000010 #
b10110101000010 2
1"
0$
1&
#746000
b100 *
b0 ?
b1 >
b10000 @
#750000
b1110100011010000110010101110100011000010010000000111101001000000010000000110110001100000010000001100100011001010110011100100000 =
b11011101101101 <
b10000000000000 ;
b10000110000011 :
0&
#755000
0"
1&
#760000
1(
b10000110000011 %
b10000110000011 +
0&
#765000
b1 6
b100001100000110 9
b0 8
b10011011011101 7
b0 3
1$
1&
#766000
b0 @
0(
#770000
0&
#775000
b1 3
b1000011000010 9
b10011011011101 8
1&
#776000
b1 @
#780000
0&
#785000
b10 3
b1111001100010110 9
b11101001001011 8
b1001101101111 7
1&
#786000
b10 @
#790000
0&
#795000
b11 3
b1011000100 9
b11010101110000 8
b10001000000001 7
1&
#796000
b11 @
#800000
0&
#805000
b100 3
b1111101011001111 9
b11100110110000 8
b1101101010011 7
1&
#806000
b100 @
#810000
0&
#815000
b101 3
b1111111011001101 9
b11011111111011 8
b1111011101110 7
1&
#816000
b101 @
#820000
0&
#825000
b110 3
b11001101 9
b11011100000100 8
b10000010101101 7
1&
#826000
b110 @
#830000
0&
#835000
b111 3
b1111111111001101 9
b11011110000110 8
b1111111010001 7
1&
#836000
b111 @
#840000
0&
#845000
b1000 3
b1001101 9
b11011101000111 8
b10000001000000 7
1&
#846000
b1000 @
#850000
0&
#855000
b1001 3
b1101 9
b11011101100111 8
b10000000001001 7
1&
#856000
b1001 @
#860000
0&
#865000
b1010 3
b1111111111101101 9
b11011101110111 8
b1111111101110 7
1&
#866000
b1010 @
#870000
0&
#875000
b1011 3
b1111111111111101 9
b11011101110000 8
b1111111111011 7
1&
#876000
b1011 @
#880000
0&
#885000
b1100 3
b101 9
b11011101101101 8
b10000000000001 7
1&
#886000
b1100 @
#890000
0&
#895000
b1101 3
b1 9
b11011101101111 8
b1111111111110 7
1&
#896000
b1101 @
#900000
0&
#905000
b1110 3
b1111111111111111 9
b1111111111101 7
1&
#906000
b1110 @
#910000
0&
#915000
b10 6
b0 9
1&
#916000
b1111 @
#920000
0&
#925000
b0 6
b11011101101111 !
b11011101101111 5
b1111111111101 #
b1111111111101 2
1"
0$
1&
#926000
b101 *
b10 ?
b11 >
b10000 @
#930000
b1110100011010000110010101110100011000010010000000111101001000000010000000111001001100000010000001100100011001010110011100100000 =
b100000000000000 <
b0 ;
b11001001000100 :
0&
#935000
0"
1&
#940000
1(
b11001001000100 %
b11001001000100 +
0&
#945000
b1 6
14
b1001101101110110 9
b0 8
b10011011011101 7
b0 3
1$
1&
#946000
b0 @
0(
#950000
0&
#955000
b1 3
b1100110110111010 9
b1101100100100011 8
1&
#956000
b1 @
#960000
0&
#965000
b10 3
b1110101101100110 9
b1100010110110101 8
b1001101101110 7
1&
#966000
b10 @
#970000
0&
#975000
b11 3
b1111101100010100 9
b1100000011011010 8
b10011011011 7
1&
#976000
b11 @
#980000
0&
#985000
b100 3
b1100001001 9
b1100000000111111 8
b1111110011110110 7
1&
#986000
b100 @
#990000
0&
#995000
b101 3
b1111111100001011 9
b1100000000001110 8
b11110011 7
1&
#996000
b101 @
#1000000
0&
#1005000
b110 3
b100001011 9
b1100000000000111 8
b1111111011110011 7
1&
#1006000
b110 @
#1010000
0&
#1015000
b111 3
b1011 9
b1100000000000010 8
b1111111111110011 7
1&
#1016000
b111 @
#1020000
0&
#1025000
b1000 3
b1111111110001011 9
b1100000000000001 8
b1110011 7
1&
#1026000
b1000 @
#1030000
0&
#1035000
b1001 3
b1111111111001011 9
b110011 7
1&
#1036000
b1001 @
#1040000
0&
#1045000
b1010 3
b1111111111101011 9
b10011 7
1&
#1046000
b1010 @
#1050000
0&
#1055000
b1011 3
b1111111111111011 9
b11 7
1&
#1056000
b1011 @
#1060000
0&
#1065000
b1100 3
b11 9
b1111111111111011 7
1&
#1066000
b1100 @
#1070000
0&
#1075000
b1101 3
b1111111111111111 9
b1100000000000000 8
b1111111111111111 7
1&
#1076000
b1101 @
#1080000
0&
#1085000
b1110 3
b1 9
b1100000000000001 8
b1111111111111101 7
1&
#1086000
b1110 @
#1090000
0&
#1095000
b10 6
b0 9
b1100000000000000 8
b1111111111111110 7
1&
#1096000
b1111 @
#1100000
0&
#1105000
b0 6
b100000000000000 !
b100000000000000 5
b10 #
b10 2
1"
0$
1&
#1106000
b110 *
b0 ?
b10 >
b10000 @
#1110000
b1110100011010000110010101110100011000010010000000111101001000000011000100110000001101010010000001100100011001010110011100100000 =
b11110111010010 <
b1110111101110000 ;
b11101010100101 :
0&
#1115000
0"
1&
#1120000
1(
b11101010100101 %
b11101010100101 +
0&
#1125000
b1 6
b1010110000111000 9
b0 8
b10011011011101 7
b0 3
1$
1&
#1126000
b0 @
0(
#1130000
0&
#1135000
b1 3
b1101111001111100 9
b1101100100100011 8
1&
#1136000
b1 @
#1140000
0&
#1145000
b10 3
b1111110000101000 9
b1100010110110101 8
b1001101101110 7
1&
#1146000
b10 @
#1150000
0&
#1155000
b11 3
b101111010110 9
b1100000011011010 8
b10011011011 7
1&
#1156000
b11 @
#1160000
0&
#1165000
b100 3
b1111100001 9
b1100000101110101 8
b110011000000 7
1&
#1166000
b100 @
#1170000
0&
#1175000
b101 3
b1111111111100011 9
b1100001001000001 8
b1000010101001 7
1&
#1176000
b101 @
#1180000
0&
#1185000
b110 3
b111100011 9
b1100000110111100 8
b111010111011 7
1&
#1186000
b110 @
#1190000
0&
#1195000
b111 3
b11100011 9
b1100000111110110 8
b111110110101 7
1&
#1196000
b111 @
#1200000
0&
#1205000
b1000 3
b1100011 9
b1100001000010101 8
b1000000110010 7
1&
#1206000
b1000 @
#1210000
0&
#1215000
b1001 3
b100011 9
b1100001000100101 8
b1000001110000 7
1&
#1216000
b1001 @
#1220000
0&
#1225000
b1010 3
b11 9
b1100001000101101 8
b1000010001111 7
1&
#1226000
b1010 @
#1230000
0&
#1235000
b1011 3
b1111111111110011 9
b1100001000110001 8
b1000010011111 7
1&
#1236000
b1011 @
#1240000
0&
#1245000
b1100 3
b1111111111111011 9
b1100001000101111 8
b1000010010111 7
1&
#1246000
b1100 @
#1250000
0&
#1255000
b1101 3
b1111111111111111 9
b1100001000101110 8
b1000010010011 7
1&
#1256000
b1101 @
#1260000
0&
#1265000
b1110 3
b1 9
b1000010010001 7
1&
#1266000
b1110 @
#1270000
0&
#1275000
b10 6
b0 9
b1000010010010 7
1&
#1276000
b1111 @
#1280000
0&
#1285000
b0 6
b11110111010010 !
b11110111010010 5
b1110111101101110 #
b1110111101101110 2
1"
0$
1&
#1286000
b111 *
b10 >
b10000 @
#1290000
b1110100011010000110010101110100011000010010000000111101001000000011000100110010001100000010000001100100011001010110011100100000 =
b11011101101101 <
b1110000000000000 ;
b100001100000101 :
0&
#1295000
0"
1&
#1300000
1(
b100001100000101 %
b100001100000101 +
0&
#1305000
b1 6
b1011110011111000 9
b0 8
b10011011011101 7
b0 3
1$
1&
#1306000
b0 @
0(
#1310000
0&
#1315000
b1 3
b1110111100111100 9
b1101100100100011 8
1&
#1316000
b1 @
#1320000
0&
