Parameter.v
// =========================================================================
// Practical 4: StarCore-1 — Single-Cycle Processor in Verilog
// =========================================================================
//
// GROUP NUMBER: 11
//
// MEMBERS:
//   - Joshua Smith,    SMTJOS022
//   - Ebrahim Bhyat,   BHYEBR002
//   - Tlangalani Tembe, TMBTLA001

`timescale 1ns / 1ps

`define WORDWIDTH 16
`define INSTRUCTION_DEPTH 16
`define DATA_DEPTH 8
`define SIM_TIME 1

GPR.v
// =========================================================================
// Practical 4: StarCore-1 — Single-Cycle Processor in Verilog
// =========================================================================
//
// GROUP NUMBER: 11
//
// MEMBERS:
//   - Joshua Smith,    SMTJOS022
//   - Ebrahim Bhyat,   BHYEBR002
//   - Tlangalani Tembe, TMBTLA001

`include "Parameter.v"

module GPR (
    input   clk,
    input   write_en,
    input   [2:0]  read_addr1,
    input   [2:0]  read_addr2,
    input   [2:0]  write_addr,
    input   [`WORDWIDTH-1:0] write_data,

    output  [`WORDWIDTH-1:0] read_data1,
    output  [`WORDWIDTH-1:0] read_data2
    

);

    reg     [`WORDWIDTH-1:0] registers [7:0];

    assign read_data1 = (read_addr1 == 3'b000) ? `WORDWIDTH'd0 : registers[read_addr1];
    assign read_data2 = (read_addr2 == 3'b000) ? `WORDWIDTH'd0 : registers[read_addr2];

    // Synchronous write port, won't write to R0
    always @(posedge clk) begin
        if (write_en == 1'b1 && write_addr != 3'b000) begin
            registers[write_addr] <= write_data;
        end
    end

endmodule

GPR_tb.v
`timescale 1ns / 1ps
`include "Parameter.v"
`include "GPR.v"

// iverilog -Wall -o gpr_sim GPR_tb.v && ./gpr_sim && gtkwave gpr_waves.vcd &

module GPR_tb;

    // Declare inputs as 'reg'
    reg                       clk;
    reg                       write_en;
    reg  [2:0]                read_addr1;
    reg  [2:0]                read_addr2;
    reg  [2:0]                write_addr;
    reg  [`WORDWIDTH-1:0]     write_data;

    // Declare outputs as 'wire'
    wire [`WORDWIDTH-1:0]     read_data1;
    wire [`WORDWIDTH-1:0]     read_data2;

    GPR uut (
        .clk(clk),
        .write_en(write_en),
        .read_addr1(read_addr1),
        .read_addr2(read_addr2),
        .write_addr(write_addr),
        .write_data(write_data),
        .read_data1(read_data1),
        .read_data2(read_data2)
    );

    // Generate the Clock (10ns period)
    initial clk = 1'b0;
    always #5 clk = ~clk;
    integer i;

    initial begin
        $dumpfile("gpr_waves.vcd");
        $dumpvars(0, GPR_tb);

        // Manually dump all 8 registers onto GTKwave
        $dumpvars(0, uut.registers[0]);
        $dumpvars(0, uut.registers[1]);
        $dumpvars(0, uut.registers[2]);
        $dumpvars(0, uut.registers[3]);
        $dumpvars(0, uut.registers[4]);
        $dumpvars(0, uut.registers[5]);
        $dumpvars(0, uut.registers[6]);
        $dumpvars(0, uut.registers[7]);


        // Initialize all inputs to 0 to prevent floating states
        write_en = 1'b0;
        read_addr1 = 3'b000;
        read_addr2 = 3'b000;
        write_addr = 3'b000;
        write_data = `WORDWIDTH'd0;

        $display("--- Starting GPR Tests ---");

        // Test 1: Write a value to R1 and read it back
        @(posedge clk); #1; 
        write_en = 1'b1;
        write_addr = 3'b001; 
        write_data = `WORDWIDTH'hAAAA; 
        
        @(posedge clk); #1; 
        write_en = 1'b0; 
        read_addr1 = 3'b001; 
        #10; 

        if (read_data1 !== `WORDWIDTH'hAAAA)
            $display("FAIL T1: Expected 0xAAAA from R1, got 0x%04h", read_data1);
        else
            $display("PASS T1: Successfully wrote and read 0xAAAA to R1");


        // Test 2: R0 Hardwire Test (Write to R0, should stay 0)
        @(posedge clk); #1;
        write_en = 1'b1;
        write_addr = 3'b000;
        write_data = `WORDWIDTH'hFFFF; // Try to overwrite R0
        
        @(posedge clk); #1;
        write_en = 1'b0;
        read_addr1 = 3'b000;
        #10;

        if (read_data1 !== `WORDWIDTH'd0)
            $display("FAIL T2: R0 was overwritten. Got 0x%04h", read_data1);
        else
            $display("PASS T2: R0 correctly hardwired to 0");

        // Test 3: Write Enable Test 
        @(posedge clk); #1;
        write_en = 1'b0; // No write permission
        write_addr = 3'b010; //  R2
        write_data = `WORDWIDTH'hBEEF; // Hehe
        
        @(posedge clk); #1;
        read_addr1 = 3'b010;
        #10;

        if (read_data1 === `WORDWIDTH'hBEEF)
            $display("FAIL T3: Wrote 0xBEEF to R2 while write_en was low!");
        else
            $display("PASS T3: Write Enable logic protected R2");

        // Test 4: Dual Read Ports (Read R1 and R2 simultaneously)
        @(posedge clk); #1;
        write_en = 1'b1;
        write_addr = 3'b010;
        write_data = `WORDWIDTH'h1234;
        
        @(posedge clk); #1;
        write_en = 1'b0;
        
        // Dual asynch read
        read_addr1 = 3'b001;
        read_addr2 = 3'b010;
        #10;

        if (read_data1 !== `WORDWIDTH'hAAAA || read_data2 !== `WORDWIDTH'h1234)
            $display("FAIL T4: Dual read failed. R1: 0x%04h, R2: 0x%04h", read_data1, read_data2);
        else
            $display("PASS T4: Dual asynchronous read successful");

        #20;
        $display("--- Tests Complete ---");
        $finish;
    end

endmodule

waves/gpr_waves.vcd
$date
	Mon May 18 09:35:13 2026
$end
$version
	Icarus Verilog
$end
$timescale
	1ps
$end
$scope module GPR_tb $end
$var wire 16 ! read_data2 [15:0] $end
$var wire 16 " read_data1 [15:0] $end
$var reg 1 # clk $end
$var reg 3 $ read_addr1 [2:0] $end
$var reg 3 % read_addr2 [2:0] $end
$var reg 3 & write_addr [2:0] $end
$var reg 16 ' write_data [15:0] $end
$var reg 1 ( write_en $end
$scope module uut $end
$var wire 1 # clk $end
$var wire 3 ) read_addr1 [2:0] $end
$var wire 3 * read_addr2 [2:0] $end
$var wire 3 + write_addr [2:0] $end
$var wire 16 , write_data [15:0] $end
$var wire 1 ( write_en $end
$var wire 16 - read_data2 [15:0] $end
$var wire 16 . read_data1 [15:0] $end
$upscope $end
$upscope $end
$scope module GPR_tb $end
$scope module uut $end
$var reg 16 / \registers[0] [15:0] $end
$upscope $end
$upscope $end
$scope module GPR_tb $end
$scope module uut $end
$var reg 16 0 \registers[1] [15:0] $end
$upscope $end
$upscope $end
$scope module GPR_tb $end
$scope module uut $end
$var reg 16 1 \registers[2] [15:0] $end
$upscope $end
$upscope $end
$scope module GPR_tb $end
$scope module uut $end
$var reg 16 2 \registers[3] [15:0] $end
$upscope $end
$upscope $end
$scope module GPR_tb $end
$scope module uut $end
$var reg 16 3 \registers[4] [15:0] $end
$upscope $end
$upscope $end
$scope module GPR_tb $end
$scope module uut $end
$var reg 16 4 \registers[5] [15:0] $end
$upscope $end
$upscope $end
$scope module GPR_tb $end
$scope module uut $end
$var reg 16 5 \registers[6] [15:0] $end
$upscope $end
$upscope $end
$scope module GPR_tb $end
$scope module uut $end
$var reg 16 6 \registers[7] [15:0] $end
$upscope $end
$upscope $end
$enddefinitions $end
$comment Show the parameter values. $end
$dumpall
$end
#0
$dumpvars
bx 6
bx 5
bx 4
bx 3
bx 2
bx 1
bx 0
bx /
b0 .
b0 -
b0 ,
b0 +
b0 *
b0 )
0(
b0 '
b0 &
b0 %
b0 $
0#
b0 "
b0 !
$end
#5000
1#
#6000
b1010101010101010 '
b1010101010101010 ,
b1 &
b1 +
1(
#10000
0#
#15000
b1010101010101010 0
1#
#16000
b1010101010101010 "
b1010101010101010 .
b1 $
b1 )
0(
#20000
0#
#25000
1#
#30000
0#
#35000
1#
#36000
b1111111111111111 '
b1111111111111111 ,
b0 &
b0 +
1(
#40000
0#
#45000
1#
#46000
b0 "
b0 .
b0 $
b0 )
0(
#50000
0#
#55000
1#
#60000
0#
#65000
1#
#66000
b1011111011101111 '
b1011111011101111 ,
b10 &
b10 +
#70000
0#
#75000
1#
#76000
bx "
bx .
b10 $
b10 )
#80000
0#
#85000
1#
#90000
0#
#95000
1#
#96000
b1001000110100 '
b1001000110100 ,
1(
#100000
0#
#105000
b1001000110100 "
b1001000110100 .
b1001000110100 1
1#
#106000
b1001000110100 !
b1001000110100 -
b1010101010101010 "
b1010101010101010 .
b10 %
b10 *
b1 $
b1 )
0(
